abi_maker/__init__.py
abi_maker/bin/abi_maker_cli.py
abi_maker/demo_abis/DFK_ABIS.json
abi_maker/demo_abis/EVO_ABIS.json
abi_maker/demo_abis/Ponzi_ABIS.json
abi_maker/demo_abis/TREASURE_ABIS.json
abi_maker/make_wrapper.py
abi_maker/template_modules/abi_contract_wrapper.py
abi_maker/template_modules/abi_multi_contract_wrapper.py
abi_maker/template_modules/credentials.py
abi_maker/template_modules/solidity_types.py
abi_maker-0.1.2.dist-info/METADATA
abi_maker-0.1.2.dist-info/WHEEL
abi_maker-0.1.2.dist-info/entry_points.txt
abi_maker-0.1.2.dist-info/RECORD
