Metadata-Version: 2.1
Name: abi-maker
Version: 0.1.2
Summary: 
Author: Athiriyya
Author-email: athiriyya@gmail.com
Requires-Python: >=3.10,<4.0
Classifier: Programming Language :: Python :: 3
Classifier: Programming Language :: Python :: 3.10
Classifier: Programming Language :: Python :: 3.11
Requires-Dist: inflection (>=0.5.1,<0.6.0)
Requires-Dist: web3 (>=6.4.0,<7.0.0)
